flake8_qa_style/__init__.py
flake8_qa_style/config.py
flake8_qa_style/plugins.py
flake8_qa_style/checkers/__init__.py
flake8_qa_style/checkers/line_checkers/__init__.py
flake8_qa_style/checkers/line_checkers/_checker_with_lines.py
flake8_qa_style/checkers/line_checkers/file_start_checker.py
flake8_qa_style/checkers/node_visitors/__init__.py
flake8_qa_style/checkers/node_visitors/_visitor_with_filename.py
flake8_qa_style/checkers/node_visitors/annotation_visitor.py
flake8_qa_style/checkers/node_visitors/assert_visitor.py
flake8_qa_style/checkers/node_visitors/function_call_visitor.py
flake8_qa_style/checkers/node_visitors/call_checkers/__init__.py
flake8_qa_style/checkers/node_visitors/call_checkers/print_checker.py
flake8_qa_style/checkers/node_visitors/call_checkers/sleep_checker.py
flake8_qa_style/errors/__init__.py
flake8_qa_style/errors/errors.py
flake8_qa_style-1.0.2.dist-info/licenses/LICENSE
tests/line_checkers/__init__.py
tests/line_checkers/test_file_start.py
tests/node_visitors_tests/__init__.py
tests/node_visitors_tests/test_annotation.py
tests/node_visitors_tests/test_assert.py
tests/node_visitors_tests/test_print.py
tests/node_visitors_tests/test_sleep.py
flake8_qa_style-1.0.2.dist-info/METADATA
flake8_qa_style-1.0.2.dist-info/WHEEL
flake8_qa_style-1.0.2.dist-info/entry_points.txt
flake8_qa_style-1.0.2.dist-info/top_level.txt
flake8_qa_style-1.0.2.dist-info/RECORD
